LICENSE
MANIFEST.in
README.markdown
setup.py
django_cache_stockpile.egg-info/PKG-INFO
django_cache_stockpile.egg-info/SOURCES.txt
django_cache_stockpile.egg-info/dependency_links.txt
django_cache_stockpile.egg-info/not-zip-safe
django_cache_stockpile.egg-info/top_level.txt
stockpile/__init__.py
stockpile/conf.py
stockpile/managers.py
stockpile/models.py
stockpile/tests/__init__.py
stockpile/tests/models.py
stockpile/tests/tests.py