Metadata-Version: 1.0
Name: django-cache-stockpile
Version: 0.1.0
Summary: A simple django ORM caching layer.
Home-page: http://github.com/streeter/django-cache-stockpile
Author: Chris Streeter
Author-email: pypi@chrisstreeter.com
License: BSD
Platform: UNKNOWN
Classifier: Framework :: Django
Classifier: Environment :: Web Environment
Classifier: Intended Audience :: Developers
Classifier: Intended Audience :: System Administrators
Classifier: Operating System :: OS Independent
Classifier: Topic :: Software Development
Classifier: License :: OSI Approved :: BSD License
Classifier: Operating System :: OS Independent
Classifier: Programming Language :: Python
Classifier: Topic :: Software Development :: Libraries :: Python Modules
